cpiextract/__init__.py
cpiextract/data_manager/APIManager.py
cpiextract/data_manager/DataManager.py
cpiextract/data_manager/LocalManager.py
cpiextract/data_manager/SQLManager.py
cpiextract/data_manager/__init__.py
cpiextract/databases/BindingDB.py
cpiextract/databases/CTD.py
cpiextract/databases/ChEMBL.py
cpiextract/databases/DTC.py
cpiextract/databases/Database.py
cpiextract/databases/DrugBank.py
cpiextract/databases/DrugCentral.py
cpiextract/databases/OTP.py
cpiextract/databases/PubChem.py
cpiextract/databases/Stitch.py
cpiextract/databases/__init__.py
cpiextract/pipelines/Comp2Prot.py
cpiextract/pipelines/Pipeline.py
cpiextract/pipelines/Prot2Comp.py
cpiextract/pipelines/__init__.py
cpiextract/servers/BiomartServer.py
cpiextract/servers/ChEMBLServer.py
cpiextract/servers/PubchemServer.py
cpiextract/servers/__init__.py
cpiextract/sql_connection/__init__.py
cpiextract/sql_connection/sql_connection.py
cpiextract/utils/__init__.py
cpiextract/utils/helper.py
cpiextract/utils/identifiers.py
cpiextract-0.1.3.dist-info/LICENSE.txt
cpiextract-0.1.3.dist-info/METADATA
cpiextract-0.1.3.dist-info/WHEEL
cpiextract-0.1.3.dist-info/top_level.txt
cpiextract-0.1.3.dist-info/RECORD
