Metadata-Version: 2.1
Name: cpiextract
Version: 0.1.3
Summary: CPIExtract is a software package to collect and harmonize small molecule and protein interactions.
Author: Andrea Piras, Shi Chenghao, Michael Sebek, Gordana Ispirova, Giulia Menichetti
Author-email: giulia.menichetti@channing.harvard.edu
License: MIT
Keywords: data-science,bioinformatics,cheminformatics,proteins,network-science,data-harmonization,binding-affinity,chemical-compounds
Classifier: Programming Language :: Python :: 3
Classifier: License :: OSI Approved :: MIT License
Classifier: Operating System :: OS Independent
License-File: LICENSE.txt
Requires-Dist: pandas
Requires-Dist: numpy
Requires-Dist: mysql-connector-python
Requires-Dist: biomart >=0.9.1
Requires-Dist: chembl-webresource-client >=0.10.8
Requires-Dist: pubchempy ==1.0.4
Requires-Dist: tqdm
Provides-Extra: interactive
Requires-Dist: jupyter ; extra == 'interactive'
